mkpassphrase/__init__.py
mkpassphrase/api.py
mkpassphrase/internal.py
mkpassphrase/main.py
mkpassphrase/wordlists/eff_large_wordlist.txt
mkpassphrase/wordlists/eff_short_wordlist_1.txt
mkpassphrase/wordlists/eff_short_wordlist_2_0.txt
mkpassphrase-2.0.0.post1.dist-info/METADATA
mkpassphrase-2.0.0.post1.dist-info/RECORD
mkpassphrase-2.0.0.post1.dist-info/WHEEL
mkpassphrase-2.0.0.post1.dist-info/entry_points.txt
mkpassphrase-2.0.0.post1.dist-info/top_level.txt
