Metadata-Version: 2.1
Name: mkpassphrase
Version: 2.0.0.post1
Summary: Word-based passphrase generator
Home-page: https://github.com/eukaryote/mkpassphrase
Author: Calvin Smith
Author-email: sapientdust+mkpassphrase@gmail.com
License: http://www.opensource.org/licenses/mit-license.php
Keywords: passphrase password
Platform: any
Classifier: Programming Language :: Python :: 2.7
Classifier: Programming Language :: Python :: 3.2
Classifier: Programming Language :: Python :: 3.3
Classifier: Programming Language :: Python :: 3.4
Classifier: Programming Language :: Python :: 3.5
Classifier: Programming Language :: Python :: 3.6
Classifier: Programming Language :: Python :: 3.7
Classifier: License :: OSI Approved :: MIT License
Classifier: Environment :: Console
Classifier: Development Status :: 5 - Production/Stable
Classifier: Topic :: Security
Classifier: Topic :: Utilities
Requires-Dist: six
Provides-Extra: develop
Requires-Dist: wheel; extra == 'develop'
Provides-Extra: testing
Requires-Dist: pytest; extra == 'testing'
Requires-Dist: mock; extra == 'testing'
Requires-Dist: pytest-cov; extra == 'testing'
Requires-Dist: pytest-pyflake8; extra == 'testing'
